[{"N":1024,"K":2,"Value":-1.6137},{"N":2048,"K":2,"Value":-1.6213},{"N":4096,"K":2,"Value":-1.6225},{"N":8192,"K":2,"Value":-1.6225},{"N":16384,"K":2,"Value":-1.6228},{"N":32768,"K":2,"Value":-1.6228},{"N":1024,"K":3,"Value":-1.6303},{"N":2048,"K":3,"Value":-1.6372},{"N":4096,"K":3,"Value":-1.638},{"N":8192,"K":3,"Value":-1.6382},{"N":16384,"K":3,"Value":-1.6386},{"N":32768,"K":3,"Value":-1.6389},{"N":1024,"K":4,"Value":-1.6484},{"N":2048,"K":4,"Value":-1.6494},{"N":4096,"K":4,"Value":-1.6514},{"N":8192,"K":4,"Value":-1.654},{"N":16384,"K":4,"Value":-1.6539},{"N":32768,"K":4,"Value":-1.654},{"N":1024,"K":5,"Value":-1.6541},{"N":2048,"K":5,"Value":-1.6575},{"N":4096,"K":5,"Value":-1.6575},{"N":8192,"K":5,"Value":-1.6588},{"N":16384,"K":5,"Value":-1.659},{"N":32768,"K":5,"Value":-1.659},{"N":1024,"K":6,"Value":-1.6587},{"N":2048,"K":6,"Value":-1.6569},{"N":4096,"K":6,"Value":-1.6629},{"N":8192,"K":6,"Value":-1.6628},{"N":16384,"K":6,"Value":-1.6629},{"N":32768,"K":6,"Value":-1.6641},{"N":1024,"K":7,"Value":-1.6612},{"N":2048,"K":7,"Value":-1.659},{"N":4096,"K":7,"Value":-1.6649},{"N":8192,"K":7,"Value":-1.666},{"N":16384,"K":7,"Value":-1.6661},{"N":32768,"K":7,"Value":-1.6664},{"N":1024,"K":8,"Value":-1.6595},{"N":2048,"K":8,"Value":-1.6648},{"N":4096,"K":8,"Value":-1.6657},{"N":8192,"K":8,"Value":-1.6674},{"N":16384,"K":8,"Value":-1.6677},{"N":32768,"K":8,"Value":-1.668}]
