[{"N":1024,"K":2,"Value":-1.6212},{"N":2048,"K":2,"Value":-1.621},{"N":4096,"K":2,"Value":-1.6222},{"N":8192,"K":2,"Value":-1.6226},{"N":16384,"K":2,"Value":-1.6226},{"N":32768,"K":2,"Value":-1.6228},{"N":1024,"K":3,"Value":-1.6322},{"N":2048,"K":3,"Value":-1.6374},{"N":4096,"K":3,"Value":-1.6375},{"N":8192,"K":3,"Value":-1.6378},{"N":16384,"K":3,"Value":-1.6387},{"N":32768,"K":3,"Value":-1.6388},{"N":1024,"K":4,"Value":-1.6505},{"N":2048,"K":4,"Value":-1.6492},{"N":4096,"K":4,"Value":-1.6526},{"N":8192,"K":4,"Value":-1.6534},{"N":16384,"K":4,"Value":-1.6537},{"N":32768,"K":4,"Value":-1.6541},{"N":1024,"K":5,"Value":-1.6454},{"N":2048,"K":5,"Value":-1.6557},{"N":4096,"K":5,"Value":-1.6578},{"N":8192,"K":5,"Value":-1.6574},{"N":16384,"K":5,"Value":-1.6593},{"N":32768,"K":5,"Value":-1.6594},{"N":1024,"K":6,"Value":-1.6615},{"N":2048,"K":6,"Value":-1.6579},{"N":4096,"K":6,"Value":-1.6605},{"N":8192,"K":6,"Value":-1.664},{"N":16384,"K":6,"Value":-1.6635},{"N":32768,"K":6,"Value":-1.6643},{"N":1024,"K":7,"Value":-1.6601},{"N":2048,"K":7,"Value":-1.663},{"N":4096,"K":7,"Value":-1.6649},{"N":8192,"K":7,"Value":-1.6661},{"N":16384,"K":7,"Value":-1.666},{"N":32768,"K":7,"Value":-1.6663},{"N":1024,"K":8,"Value":-1.6547},{"N":2048,"K":8,"Value":-1.6623},{"N":4096,"K":8,"Value":-1.666},{"N":8192,"K":8,"Value":-1.6667},{"N":16384,"K":8,"Value":-1.6674},{"N":32768,"K":8,"Value":-1.6681}]
